{
  "generator-jhipster": {
    "applicationType": "monolith",
    "authenticationType": "jwt",
    "baseName": "coffee",
    "buildTool": "maven",
    "cacheProvider": "no",
    "clientFramework": "angular",
    "clientTestFrameworks": [],
    "clientTheme": "none",
    "creationTimestamp": 1732900873205,
    "databaseType": "sql",
    "devDatabaseType": "h2Disk",
    "devServerPort": 4200,
    "enableGradleEnterprise": null,
    "enableHibernateCache": false,
    "enableSwaggerCodegen": false,
    "enableTranslation": true,
    "entities": ["Product"],
    "feignClient": null,
    "gradleEnterpriseHost": null,
    "jhipsterVersion": "8.2.1",
    "jwtSecretKey": "MWQ0OWM2MDczYTU5MDYzMjk1ZWJmYTMwNTkyZTA2NTg3NGZlYjI3NWQ5M2FmZjI3MDlmY2M2ODNlNjU3ZGU4ZmUzZWI5MDdjNzBkNmU4N2MxODdlYzYwNzM5N2YwNTM4MGRmYzYyZDhjMGQ1ZjI2Mzg3ODVkYWU2ZTMzZDA0MGI=",
    "languages": ["en", "ru", "uz-Latn-uz"],
    "lastLiquibaseTimestamp": 1732901596000,
    "messageBroker": false,
    "microfrontend": null,
    "microfrontends": [],
    "nativeLanguage": "en",
    "packageName": "org.abror",
    "prodDatabaseType": "postgresql",
    "reactive": false,
    "searchEngine": false,
    "serverPort": null,
    "serverSideOptions": [],
    "serviceDiscoveryType": false,
    "syncUserWithIdp": null,
    "testFrameworks": [],
    "websocket": false,
    "withAdminUi": true
  }
}
